_secupy.cp310-win_arm64.pyd
secupy/__init__.py
secupy/__main__.py
secupy/commands/activate.py
secupy/commands/build.py
secupy/commands/console.py
secupy/commands/module.py
secupy/commands/status.py
secupy/commands/__init__.py
secupy-1.2.2.data/platlib/msvcp140-ed73c6745a7b3e203ff141e8ac2db969.dll
secupy-1.2.2.dist-info/DELVEWHEEL
secupy-1.2.2.dist-info/entry_points.txt
secupy-1.2.2.dist-info/LICENSE
secupy-1.2.2.dist-info/METADATA
secupy-1.2.2.dist-info/RECORD
secupy-1.2.2.dist-info/top_level.txt
secupy-1.2.2.dist-info/WHEEL
