Metadata-Version: 2.1
Name: secupy
Version: 1.2.2
Summary: Advanced encryption protecting your python codebase.
Home-page: https://secupy.com/
Author: Di2MA
Author-email: secupy@di2ma.com
License: Other/Proprietary License
Project-URL: Dashboard, https://secupy.com/
Keywords: encryption source aes remote
Classifier: Development Status :: 5 - Production/Stable
Classifier: Intended Audience :: Developers
Classifier: Intended Audience :: Education
Classifier: Intended Audience :: Information Technology
Classifier: Intended Audience :: Other Audience
Classifier: Intended Audience :: Science/Research
Classifier: Intended Audience :: System Administrators
Classifier: Topic :: Security
Classifier: Topic :: Security :: Cryptography
Classifier: Topic :: Software Development
Classifier: Topic :: Software Development :: Libraries
Classifier: Topic :: Software Development :: Libraries :: Python Modules
Classifier: Topic :: System :: Software Distribution
Classifier: Topic :: Utilities
Classifier: License :: Other/Proprietary License
Classifier: Operating System :: MacOS
Classifier: Operating System :: Microsoft :: Windows
Classifier: Operating System :: POSIX :: Linux
Classifier: Programming Language :: Python :: 3.8
Classifier: Programming Language :: Python :: 3.9
Classifier: Programming Language :: Python :: 3.10
Classifier: Programming Language :: Python :: 3.11
Classifier: Programming Language :: Python :: 3.12
Classifier: Programming Language :: Python :: 3.13
Requires-Python: >3.7
License-File: LICENSE
Requires-Dist: setuptools>=42
Requires-Dist: tqdm>=4.64.0
Requires-Dist: requests>=2.27.1
Provides-Extra: test
Requires-Dist: pytest; extra == "test"
